bddrest/__init__.py
bddrest/cli.py
bddrest/connectors.py
bddrest/context.py
bddrest/exceptions.py
bddrest/headerset.py
bddrest/helpers.py
bddrest/proxy.py
bddrest/response.py
bddrest/authoring/__init__.py
bddrest/authoring/given.py
bddrest/authoring/manipulation.py
bddrest/authoring/story.py
bddrest/documentary/__init__.py
bddrest/documentary/cli.py
bddrest/documentary/curl.py
bddrest/documentary/documenter.py
bddrest/documentary/helpers.py
bddrest/documentary/formatters/__init__.py
bddrest/documentary/formatters/base.py
bddrest/documentary/formatters/html.py
bddrest/documentary/formatters/markdown.py
bddrest/specification/__init__.py
bddrest/specification/alteredcall.py
bddrest/specification/call.py
bddrest/specification/firstcall.py
bddrest-6.2.3.dist-info/licenses/LICENSE
bddrest-6.2.3.dist-info/METADATA
bddrest-6.2.3.dist-info/WHEEL
bddrest-6.2.3.dist-info/entry_points.txt
bddrest-6.2.3.dist-info/top_level.txt
bddrest-6.2.3.dist-info/RECORD
